akutils/__init__.py
akutils/pandas_read_files.py
akutils/pandas_type_conversion.py
akutils/project_api.py
akutils/utils_functions.py
akutils/tests/unit/test_pandas_columns_to_float.py
akutils_tmp-0.0.1.dist-info/LICENSE
akutils_tmp-0.0.1.dist-info/METADATA
akutils_tmp-0.0.1.dist-info/WHEEL
akutils_tmp-0.0.1.dist-info/top_level.txt
akutils_tmp-0.0.1.dist-info/RECORD
