Metadata-Version: 2.1
Name: akutils_tmp
Version: 0.0.1
Summary: A utility library providing generic methods for performing recurrent data manipulation in Pandas and Python.
Author-email: Alex0x4b <alex0x4b.git.su1b4@slmail.me>
Project-URL: Homepage, https://github.com/Alex0x4b/akutils
Requires-Python: <3.11,>=3.9
License-File: LICENSE
Requires-Dist: pandas ==2.1.4
Requires-Dist: pyarrow >=14.0.0
Requires-Dist: numpy >=1.26.0
Requires-Dist: PyYAML >=6.0
Requires-Dist: flake8 >=5.0.4
Requires-Dist: pytest >=7.2.2
Requires-Dist: pytest-cov >=4.0.0
Requires-Dist: mypy >=1.9.0
Requires-Dist: pandas-stubs >=2.2.0.24
